imas/__init__.py
imas/__main__.py
imas/_to_xarray.py
imas/_util.py
imas/_version.py
imas/db_entry.py
imas/dd_zip.py
imas/exception.py
imas/ids_base.py
imas/ids_convert.py
imas/ids_coordinates.py
imas/ids_data_type.py
imas/ids_defs.py
imas/ids_factory.py
imas/ids_identifiers.py
imas/ids_metadata.py
imas/ids_path.py
imas/ids_primitive.py
imas/ids_struct_array.py
imas/ids_structure.py
imas/ids_toplevel.py
imas/setup_logging.py
imas/training.py
imas/util.py
imas/assets/IDSDef2MDSpreTree.xsl
imas/assets/IDS_fake_toplevel.xml
imas/assets/IDS_minimal.xml
imas/assets/IDS_minimal_2.xml
imas/assets/IDS_minimal_struct_array.xml
imas/assets/IDS_minimal_types.xml
imas/assets/ITER_134173_106_core_profiles.ids
imas/assets/ITER_134173_106_equilibrium.ids
imas/assets/README.md
imas/assets/core_profiles.ids
imas/assets/equilibrium.ids
imas/backends/__init__.py
imas/backends/db_entry_impl.py
imas/backends/imas_core/__init__.py
imas/backends/imas_core/al_context.py
imas/backends/imas_core/db_entry_al.py
imas/backends/imas_core/db_entry_helpers.py
imas/backends/imas_core/imas_interface.py
imas/backends/imas_core/mdsplus_model.py
imas/backends/imas_core/uda_support.py
imas/backends/netcdf/__init__.py
imas/backends/netcdf/db_entry_nc.py
imas/backends/netcdf/ids2nc.py
imas/backends/netcdf/ids_tensorizer.py
imas/backends/netcdf/iterators.py
imas/backends/netcdf/nc2ids.py
imas/backends/netcdf/nc_metadata.py
imas/backends/netcdf/nc_validate.py
imas/command/cli.py
imas/command/db_analysis.py
imas/command/helpers.py
imas/command/timer.py
imas/test/test_all_dd_versions.py
imas/test/test_cli.py
imas/test/test_dbentry.py
imas/test/test_dd_zip.py
imas/test/test_deepcopy.py
imas/test/test_exception.py
imas/test/test_get_sample.py
imas/test/test_hash.py
imas/test/test_helpers.py
imas/test/test_identifiers.py
imas/test/test_ids2nc.py
imas/test/test_ids_ascii_data.py
imas/test/test_ids_convert.py
imas/test/test_ids_coordinates.py
imas/test/test_ids_data_type.py
imas/test/test_ids_factory.py
imas_python-2.1.0.post1.dist-info/licenses/LICENSE.txt
imas_python-2.1.0.post1.dist-info/METADATA
imas_python-2.1.0.post1.dist-info/WHEEL
imas_python-2.1.0.post1.dist-info/entry_points.txt
imas_python-2.1.0.post1.dist-info/top_level.txt
imas_python-2.1.0.post1.dist-info/RECORD
