Metadata-Version: 2.4
Name: imas-python
Version: 2.1.0.post1
Summary: Pythonic wrappers for the IMAS Access Layer
Author: ITER Organization
Author-email: Karel Lucas van de Plassche <karelvandeplassche@gmail.com>, Daan van Vugt <dvanvugt@ignitioncomputing.com>, Maarten Sebregts <msebregts@ignitioncomputing.com>, imas-support@iter.org
License:                   GNU LESSER GENERAL PUBLIC LICENSE
Project-URL: homepage, https://github.com/iterorganization/imas-python
Classifier: Development Status :: 5 - Production/Stable
Classifier: Environment :: Console
Classifier: Environment :: Plugins
Classifier: Environment :: X11 Applications
Classifier: Framework :: Flake8
Classifier: Framework :: IPython
Classifier: Framework :: Matplotlib
Classifier: Framework :: Pytest
Classifier: Framework :: Sphinx
Classifier: Intended Audience :: Developers
Classifier: Intended Audience :: Science/Research
Classifier: Intended Audience :: System Administrators
Classifier: License :: OSI Approved :: GNU Lesser General Public License v3 (LGPLv3)
Classifier: Natural Language :: English
Classifier: Operating System :: POSIX
Classifier: Operating System :: POSIX :: Linux
Classifier: Programming Language :: Python
Classifier: Programming Language :: Python :: 3
Classifier: Programming Language :: Python :: 3.8
Classifier: Programming Language :: Python :: 3.9
Classifier: Programming Language :: Unix Shell
Classifier: Topic :: Database
Classifier: Topic :: Database :: Front-Ends
Classifier: Topic :: Scientific/Engineering
Classifier: Topic :: Scientific/Engineering :: Physics
Classifier: Topic :: Scientific/Engineering :: Visualization
Classifier: Topic :: Software Development :: Libraries
Classifier: Topic :: Software Development :: Libraries :: Python Modules
Classifier: Topic :: System
Classifier: Topic :: System :: Software Distribution
Classifier: Topic :: Utilities
Requires-Python: >=3.7
License-File: LICENSE.txt
Requires-Dist: numpy>=1.15.4
Requires-Dist: rich
Requires-Dist: scipy
Requires-Dist: click
Requires-Dist: importlib_resources; python_version < "3.9"
Requires-Dist: packaging
Requires-Dist: xxhash>=2
Requires-Dist: imas_data_dictionaries
Requires-Dist: imas_core
Provides-Extra: all
Requires-Dist: imas-python[docs,test]; extra == "all"
Provides-Extra: docs
Requires-Dist: sphinx<7.0.0,>=6.0.0; extra == "docs"
Requires-Dist: sphinx-autosummary-accessors>=0.1.2; extra == "docs"
Requires-Dist: sphinx-immaterial<0.12,>=0.11.0; extra == "docs"
Requires-Dist: sphinx-click; extra == "docs"
Provides-Extra: netcdf
Requires-Dist: netCDF4>=1.4.1; extra == "netcdf"
Provides-Extra: h5py
Requires-Dist: h5py; extra == "h5py"
Provides-Extra: xarray
Requires-Dist: xarray; extra == "xarray"
Provides-Extra: saxonche
Requires-Dist: saxonche; extra == "saxonche"
Provides-Extra: test
Requires-Dist: pytest>=5.4.1; extra == "test"
Requires-Dist: pytest-cov>=0.6; extra == "test"
Requires-Dist: pytest-xdist; extra == "test"
Requires-Dist: pytest-randomly; extra == "test"
Requires-Dist: matplotlib; extra == "test"
Requires-Dist: asv==0.6.1; extra == "test"
Requires-Dist: virtualenv; extra == "test"
Requires-Dist: pint; extra == "test"
Requires-Dist: imas-python[h5py,netcdf,saxonche,xarray]; extra == "test"
Dynamic: license-file
